loadwright/__init__.py
loadwright/io.py
loadwright/logger.py
loadwright/py.typed
loadwright/runner.py
loadwright/user.py
loadwright/viewer.py
loadwright-0.2.0.dist-info/METADATA
loadwright-0.2.0.dist-info/WHEEL
loadwright-0.2.0.dist-info/top_level.txt
loadwright-0.2.0.dist-info/RECORD
